Metadata-Version: 1.0
Name: daydayup
Version: 1.3.2
Summary: Daily report authoring tool for baixingers
Home-page: https://github.com/onesuper/daydayup
Author: onesuper
Author-email: onesuperclark@gmail.com
License: MIT
Platform: any
